isapilib/__init__.py
isapilib/connection.py
isapilib/exceptions.py
isapilib/models.py
isapilib/management/__init__.py
isapilib/management/commands/__init__.py
isapilib/management/commands/external_migrate.py
isapilib-1.3.4.dist-info/METADATA
isapilib-1.3.4.dist-info/WHEEL
isapilib-1.3.4.dist-info/top_level.txt
isapilib-1.3.4.dist-info/RECORD
