Metadata-Version: 2.1
Name: isapilib
Version: 1.3.4
Requires-Dist: django (>=4.2)
